backpy/__init__.py
backpy/__main__.py
backpy/_commons.py
backpy/custom_plt.py
backpy/exception.py
backpy/flex_data.py
backpy/main.py
backpy/stats.py
backpy/strategy.py
backpy/utils.py
backpy/assets/icon128x.png
backpyf-1.0.0.post1.dist-info/licenses/LICENSE
backpyf-1.0.0.post1.dist-info/METADATA
backpyf-1.0.0.post1.dist-info/WHEEL
backpyf-1.0.0.post1.dist-info/entry_points.txt
backpyf-1.0.0.post1.dist-info/top_level.txt
backpyf-1.0.0.post1.dist-info/RECORD
