Metadata-Version: 2.4
Name: backpyf
Version: 1.0.0.post1
Summary: BackPy is a library made in python for back testing in financial markets.
Author-email: Diego Cores <89626622+diego-cores@users.noreply.github.com>
License-Expression: MIT
Project-URL: Homepage, https://github.com/diego-cores/backpy
Classifier: Programming Language :: Python :: 3
Classifier: Operating System :: OS Independent
Requires-Python: >=3.10
License-File: LICENSE
Requires-Dist: pandas>=2.3.0
Requires-Dist: numpy>=2.3.2
Requires-Dist: matplotlib>=3.7.5
Requires-Dist: pillow>=11.3.0
Provides-Extra: optional
Requires-Dist: yfinance==0.2.50; extra == "optional"
Requires-Dist: binance-connector==3.10.0; extra == "optional"
Requires-Dist: binance-futures-connector==4.1.0; extra == "optional"
Provides-Extra: dev
Requires-Dist: matplotlib-stubs; extra == "dev"
Requires-Dist: pandas-stubs; extra == "dev"
Requires-Dist: pyrefly; extra == "dev"
Dynamic: license-file
